humano/__init__.py
humano/cli.py
humano/main.py
humano-2.0.1.dist-info/licenses/LICENSE
humano-2.0.1.dist-info/METADATA
humano-2.0.1.dist-info/WHEEL
humano-2.0.1.dist-info/entry_points.txt
humano-2.0.1.dist-info/top_level.txt
humano-2.0.1.dist-info/RECORD
