Metadata-Version: 2.4
Name: humano
Version: 2.0.1
Summary: Advanced AI text humanization with context-aware processing, personality injection, and sophisticated NLP transformations.
Author-email: Khushiyant <khushiyant2002@gmail.com>
License: MIT
Project-URL: Homepage, https://github.com/khushiyant/humano
Project-URL: Repository, https://github.com/khushiyant/humano
Project-URL: Documentation, https://github.com/khushiyant/humano#readme
Project-URL: Bug Tracker, https://github.com/khushiyant/humano/issues
Keywords: ai,text,humanization,nlp,context-aware,personality,natural-language,transformation,semantic,pattern-recognition
Classifier: Development Status :: 4 - Beta
Classifier: Intended Audience :: Developers
Classifier: Intended Audience :: Science/Research
Classifier: Intended Audience :: Information Technology
Classifier: Programming Language :: Python :: 3
Classifier: Programming Language :: Python :: 3.10
Classifier: Programming Language :: Python :: 3.11
Classifier: Programming Language :: Python :: 3.12
Classifier: Topic :: Text Processing :: Linguistic
Classifier: Topic :: Scientific/Engineering :: Artificial Intelligence
Classifier: Topic :: Software Development :: Libraries :: Python Modules
Classifier: Natural Language :: English
Requires-Python: >=3.10
License-File: LICENSE
Provides-Extra: ai
Requires-Dist: openai>=1.0.0; extra == "ai"
Provides-Extra: dev
Requires-Dist: pytest>=7.0; extra == "dev"
Requires-Dist: black>=23.0; extra == "dev"
Requires-Dist: flake8>=6.0; extra == "dev"
Requires-Dist: mypy>=1.5; extra == "dev"
Requires-Dist: build>=0.10.0; extra == "dev"
Requires-Dist: twine>=4.0.0; extra == "dev"
Dynamic: license-file
